kanka/__init__.py
kanka/main.py
kanka-0.1.2.dist-info/LICENSE
kanka-0.1.2.dist-info/METADATA
kanka-0.1.2.dist-info/WHEEL
kanka-0.1.2.dist-info/top_level.txt
kanka-0.1.2.dist-info/RECORD
